setup.py
tornadopush/__init__.py
tornadopush/__main__.py
tornadopush/assets.py
tornadopush/cli.py
tornadopush/client.py
tornadopush.egg-info/PKG-INFO
tornadopush.egg-info/SOURCES.txt
tornadopush.egg-info/dependency_links.txt
tornadopush.egg-info/entry_points.txt
tornadopush.egg-info/not-zip-safe
tornadopush.egg-info/requires.txt
tornadopush.egg-info/top_level.txt
tornadopush/server/__init__.py
tornadopush/server/base.py
tornadopush/server/handlers.py
tornadopush/server/presence.py
tornadopush/server/queue.py
tornadopush/static/eventsource.js
tornadopush/static/presence.js
tornadopush/static/push.js
tornadopush/static/websocket.js