Metadata-Version: 1.0
Name: tornadopush
Version: 0.8.1
Summary: Push and presence server built with Tornado and Redis
Home-page: http://github.com/frascoweb/tornadopush
Author: Maxime Bouroumeau-Fuseau
Author-email: maxime.bouroumeau@gmail.com
License: MIT
Platform: any
